spotify_klio_cli/__init__.py
spotify_klio_cli/cli.py
spotify_klio_cli/cli_utils.py
spotify_klio_cli/commands/__init__.py
spotify_klio_cli/commands/job/__init__.py
spotify_klio_cli/commands/job/benchmark.py
spotify_klio_cli/commands/job/gke.py
spotify_klio_cli/commands/job/profile.py
spotify_klio_cli/commands/job/profile_queries.py
spotify_klio_cli/commands/job/publisher.py
spotify_klio_cli/commands/job/run.py
spotify_klio_cli/commands/job/verify.py
spotify_klio_cli-21.9.0.dev1.dist-info/METADATA
spotify_klio_cli-21.9.0.dev1.dist-info/WHEEL
spotify_klio_cli-21.9.0.dev1.dist-info/dependency_links.txt
spotify_klio_cli-21.9.0.dev1.dist-info/entry_points.txt
spotify_klio_cli-21.9.0.dev1.dist-info/top_level.txt
spotify_klio_cli-21.9.0.dev1.dist-info/RECORD
